pai/__init__.py
pai/cli.py
pai/code_exec.py
pai/console.py
pai/history.py
pai/llms/__init__.py
pai/llms/chat_gpt.py
pai/llms/fake.py
pai/llms/llama.py
pai/llms/llm_protocol.py
pai/repl.py
pai/version.py
pai_repl-0.1.19.dist-info/LICENSE.md
pai_repl-0.1.19.dist-info/METADATA
pai_repl-0.1.19.dist-info/WHEEL
pai_repl-0.1.19.dist-info/entry_points.txt
pai_repl-0.1.19.dist-info/RECORD
