Metadata-Version: 2.1
Name: pai-repl
Version: 0.1.19
Summary: Python REPL with LLM integration
Author: Alex Wiles
Author-email: xwiles@gmail.com
Requires-Python: >=3.8,<4.0
Classifier: Programming Language :: Python :: 3
Classifier: Programming Language :: Python :: 3.8
Classifier: Programming Language :: Python :: 3.9
Classifier: Programming Language :: Python :: 3.10
Classifier: Programming Language :: Python :: 3.11
Provides-Extra: llama
Requires-Dist: llama-cpp-python (>=0.1.78,<0.2.0) ; extra == "llama"
Requires-Dist: openai (==0.27.8)
Requires-Dist: prompt_toolkit (==3.0.39)
